{"objekter": [{"egenskaper": [{"datatype": 2, "id": 1313, "datatype_tekst": "Tall", "navn": "Lengde", "enhet": {"kortnavn": "m", "id": 1, "navn": "Meter"}, "verdi": 12.25}, {"datatype": 2, "id": 1971, "datatype_tekst": "Tall", "navn": "Lengste spenn", "enhet": {"kortnavn": "m", "id": 1, "navn": "Meter"}, "verdi": 11.25}, {"datatype": 1, "datatype_tekst": "Tekst", "verdi": "Nordskj\u00f8rbrua", "id": 1080, "navn": "Navn"}, {"datatype": 30, "navn": "Vedlikeholdsansvarlig", "datatype_tekst": "FlerverdiAttributt, Tekst", "id": 8969, "enum_id": 11812, "verdi": "Vegvesenet/Fylkeskommunen"}, {"datatype": 30, "navn": "Materialtype", "datatype_tekst": "FlerverdiAttributt, Tekst", "id": 1404, "enum_id": 12327, "verdi": "St\u00e5l"}, {"datatype": 2, "datatype_tekst": "Tall", "verdi": 16, "id": 11180, "navn": "Opprinnelig F-Nr"}, {"datatype": 30, "navn": "Byggverkstype", "datatype_tekst": "FlerverdiAttributt, Tekst", "id": 9182, "enum_id": 12480, "verdi": "St\u00e5lbjelkebru (363)"}, {"datatype": 2, "datatype_tekst": "Tall", "verdi": 99, "id": 2175, "navn": "Nummer"}, {"datatype": 30, "navn": "Brukategori", "datatype_tekst": "FlerverdiAttributt, Tekst", "id": 1263, "enum_id": 7304, "verdi": "Vegbru"}], "href": "https://www.utv.vegvesen.no/nvdb/api/v2/vegobjekter/60/272297638", "lokasjon": {"vegreferanser": [{"status": "V", "nummer": 14, "fylke": 16, "fra_meter": 40796, "til_meter": 40808, "kommune": 0, "hp": 1, "kortform": "1600 Fv14 hp1 m40796-40808", "kategori": "F"}], "vegavdelinger": [16], "kommuner": [1632], "geometri": {"srid": 32633, "wkt": "LINESTRING Z (269154.16748 7118504.75374 5.47161, 269157.12891 7118502.46094 5.39, 269162.20312 7118498.4043 5.31, 269163.39132 7118497.49815 5.29538)"}, "fylker": [16], "stedfestinger": [{"retning": "MED", "til_posisjon": 0.964677381321025, "veglenkeid": 72405, "kortform": "0.961009472720665-0.964677381321025@72405", "fra_posisjon": 0.961009472720665}], "regioner": [4], "strekningslengde": 12, "kontraktsomr\u00e5der": [{"navn": "1601 Fosen 2009-2014"}, {"navn": "1601 Fosen 2014-2019"}]}, "id": 272297638, "metadata": {"versjon": 1, "startdato": "1950-01-01", "type": {"id": 60, "navn": "Bru"}, "sist_modifisert": "2017-08-02 15:48:55"}}, {"egenskaper": [{"datatype": 2, "id": 1313, "datatype_tekst": "Tall", "navn": "Lengde", "enhet": {"kortnavn": "m", "id": 1, "navn": "Meter"}, "verdi": 5.04}, {"datatype": 2, "id": 1971, "datatype_tekst": "Tall", "navn": "Lengste spenn", "enhet": {"kortnavn": "m", "id": 1, "navn": "Meter"}, "verdi": 4.82}, {"datatype": 1, "datatype_tekst": "Tekst", "verdi": "G\u00e5sen", "id": 1080, "navn": "Navn"}, {"datatype": 30, "navn": "Vedlikeholdsansvarlig", "datatype_tekst": "FlerverdiAttributt, Tekst", "id": 8969, "enum_id": 11812, "verdi": "Vegvesenet/Fylkeskommunen"}, {"datatype": 30, "navn": "Materialtype", "datatype_tekst": "FlerverdiAttributt, Tekst", "id": 1404, "enum_id": 12325, "verdi": "Betong"}, {"datatype": 2, "datatype_tekst": "Tall", "verdi": 16, "id": 11180, "navn": "Opprinnelig F-Nr"}, {"datatype": 30, "navn": "Byggverkstype", "datatype_tekst": "FlerverdiAttributt, Tekst", "id": 9182, "enum_id": 12400, "verdi": "Platebru (219)"}, {"datatype": 2, "datatype_tekst": "Tall", "verdi": 426, "id": 2175, "navn": "Nummer"}, {"datatype": 30, "navn": "Brukategori", "datatype_tekst": "FlerverdiAttributt, Tekst", "id": 1263, "enum_id": 7304, "verdi": "Vegbru"}], "href": "https://www.utv.vegvesen.no/nvdb/api/v2/vegobjekter/60/272298567", "lokasjon": {"vegreferanser": [{"status": "V", "nummer": 32, "fylke": 16, "fra_meter": 3329, "til_meter": 3334, "kommune": 0, "hp": 1, "kortform": "1600 Fv32 hp1 m3329-3334", "kategori": "F"}], "vegavdelinger": [16], "kommuner": [1630], "geometri": {"srid": 32633, "wkt": "LINESTRING Z (258940.60579 7112665.15431 10.71095, 258937.40039 7112668.08984 10.8, 258936.93619 7112668.54857 10.8)"}, "fylker": [16], "stedfestinger": [{"retning": "MED", "til_posisjon": 0.491381368900912, "veglenkeid": 72409, "kortform": "0.490645164311099-0.491381368900912@72409", "fra_posisjon": 0.490645164311099}], "regioner": [4], "strekningslengde": 5, "kontraktsomr\u00e5der": [{"navn": "1601 Fosen 2009-2014"}, {"navn": "1601 Fosen 2014-2019"}]}, "id": 272298567, "metadata": {"versjon": 1, "startdato": "1950-01-01", "type": {"id": 60, "navn": "Bru"}, "sist_modifisert": "2017-08-02 15:48:55"}}, {"egenskaper": [{"datatype": 2, "id": 1313, "datatype_tekst": "Tall", "navn": "Lengde", "enhet": {"kortnavn": "m", "id": 1, "navn": "Meter"}, "verdi": 13.25}, {"datatype": 2, "id": 1971, "datatype_tekst": "Tall", "navn": "Lengste spenn", "enhet": {"kortnavn": "m", "id": 1, "navn": "Meter"}, "verdi": 12.65}, {"datatype": 1, "datatype_tekst": "Tekst", "verdi": "Svana", "id": 1080, "navn": "Navn"}, {"datatype": 30, "navn": "Vedlikeholdsansvarlig", "datatype_tekst": "FlerverdiAttributt, Tekst", "id": 8969, "enum_id": 11812, "verdi": "Vegvesenet/Fylkeskommunen"}, {"datatype": 30, "navn": "Materialtype", "datatype_tekst": "FlerverdiAttributt, Tekst", "id": 1404, "enum_id": 12325, "verdi": "Betong"}, {"datatype": 2, "datatype_tekst": "Tall", "verdi": 16, "id": 11180, "navn": "Opprinnelig F-Nr"}, {"datatype": 30, "navn": "Byggverkstype", "datatype_tekst": "FlerverdiAttributt, Tekst", "id": 9182, "enum_id": 12475, "verdi": "Bjelkebru (359)"}, {"datatype": 2, "datatype_tekst": "Tall", "verdi": 428, "id": 2175, "navn": "Nummer"}, {"datatype": 30, "navn": "Brukategori", "datatype_tekst": "FlerverdiAttributt, Tekst", "id": 1263, "enum_id": 7304, "verdi": "Vegbru"}], "href": "https://www.utv.vegvesen.no/nvdb/api/v2/vegobjekter/60/272298580", "lokasjon": {"vegreferanser": [{"status": "V", "nummer": 32, "fylke": 16, "fra_meter": 3558, "til_meter": 3571, "kommune": 0, "hp": 1, "kortform": "1600 Fv32 hp1 m3558-3571", "kategori": "F"}], "vegavdelinger": [16], "kommuner": [1630], "geometri": {"srid": 32633, "wkt": "LINESTRING Z (258833.429 7112865.66011 6.12856, 258828 7112874.58984 6.2, 258826.66607 7112876.76224 6.2)"}, "fylker": [16], "stedfestinger": [{"retning": "MED", "til_posisjon": 0.526277466458029, "veglenkeid": 72409, "kortform": "0.524363334524516-0.526277466458029@72409", "fra_posisjon": 0.524363334524516}], "regioner": [4], "strekningslengde": 13, "kontraktsomr\u00e5der": [{"navn": "1601 Fosen 2009-2014"}, {"navn": "1601 Fosen 2014-2019"}]}, "id": 272298580, "metadata": {"versjon": 1, "startdato": "1950-01-01", "type": {"id": 60, "navn": "Bru"}, "sist_modifisert": "2017-08-02 15:48:55"}}, {"egenskaper": [{"datatype": 2, "id": 1313, "datatype_tekst": "Tall", "navn": "Lengde", "enhet": {"kortnavn": "m", "id": 1, "navn": "Meter"}, "verdi": 3.01}, {"datatype": 1, "datatype_tekst": "Tekst", "verdi": "Flatnes", "id": 1080, "navn": "Navn"}, {"datatype": 30, "navn": "Vedlikeholdsansvarlig", "datatype_tekst": "FlerverdiAttributt, Tekst", "id": 8969, "enum_id": 11812, "verdi": "Vegvesenet/Fylkeskommunen"}, {"datatype": 30, "navn": "Materialtype", "datatype_tekst": "FlerverdiAttributt, Tekst", "id": 1404, "enum_id": 12327, "verdi": "St\u00e5l"}, {"datatype": 2, "datatype_tekst": "Tall", "verdi": 16, "id": 11180, "navn": "Opprinnelig F-Nr"}, {"datatype": 30, "navn": "Byggverkstype", "datatype_tekst": "FlerverdiAttributt, Tekst", "id": 9182, "enum_id": 12363, "verdi": "R\u00f8r, korrugert (145)"}, {"datatype": 2, "datatype_tekst": "Tall", "verdi": 688, "id": 2175, "navn": "Nummer"}, {"datatype": 30, "navn": "Brukategori", "datatype_tekst": "FlerverdiAttributt, Tekst", "id": 1263, "enum_id": 7305, "verdi": "Bru i fylling"}], "href": "https://www.utv.vegvesen.no/nvdb/api/v2/vegobjekter/60/272336944", "lokasjon": {"vegreferanser": [{"status": "V", "nummer": 50, "fylke": 16, "fra_meter": 70, "til_meter": 73, "kommune": 0, "hp": 1, "kortform": "1600 Fv50 hp1 m70-73", "kategori": "F"}], "vegavdelinger": [16], "kommuner": [1630], "geometri": {"srid": 32633, "wkt": "LINESTRING Z (265601.86744 7101900.81105 8.2, 265598.98319 7101900.01361 8.2)"}, "fylker": [16], "stedfestinger": [{"retning": "MED", "til_posisjon": 0.00704647127753259, "veglenkeid": 72415, "kortform": "0.00673382141013636-0.00704647127753259@72415", "fra_posisjon": 0.00673382141013636}], "regioner": [4], "strekningslengde": 3, "kontraktsomr\u00e5der": [{"navn": "1601 Fosen 2009-2014"}, {"navn": "1601 Fosen 2014-2019"}]}, "id": 272336944, "metadata": {"versjon": 1, "startdato": "1950-01-01", "type": {"id": 60, "navn": "Bru"}, "sist_modifisert": "2017-08-02 15:48:55"}}, {"egenskaper": [{"datatype": 2, "id": 1313, "datatype_tekst": "Tall", "navn": "Lengde", "enhet": {"kortnavn": "m", "id": 1, "navn": "Meter"}, "verdi": 3.6}, {"datatype": 2, "id": 1971, "datatype_tekst": "Tall", "navn": "Lengste spenn", "enhet": {"kortnavn": "m", "id": 1, "navn": "Meter"}, "verdi": 3.05}, {"datatype": 1, "datatype_tekst": "Tekst", "verdi": "Stupet", "id": 1080, "navn": "Navn"}, {"datatype": 30, "navn": "Vedlikeholdsansvarlig", "datatype_tekst": "FlerverdiAttributt, Tekst", "id": 8969, "enum_id": 11812, "verdi": "Vegvesenet/Fylkeskommunen"}, {"datatype": 30, "navn": "Materialtype", "datatype_tekst": "FlerverdiAttributt, Tekst", "id": 1404, "enum_id": 12325, "verdi": "Betong"}, {"datatype": 2, "datatype_tekst": "Tall", "verdi": 16, "id": 11180, "navn": "Opprinnelig F-Nr"}, {"datatype": 30, "navn": "Byggverkstype", "datatype_tekst": "FlerverdiAttributt, Tekst", "id": 9182, "enum_id": 12395, "verdi": "Platebru (211)"}, {"datatype": 2, "datatype_tekst": "Tall", "verdi": 13, "id": 2175, "navn": "Nummer"}, {"datatype": 30, "navn": "Brukategori", "datatype_tekst": "FlerverdiAttributt, Tekst", "id": 1263, "enum_id": 7304, "verdi": "Vegbru"}], "href": "https://www.utv.vegvesen.no/nvdb/api/v2/vegobjekter/60/272765375", "lokasjon": {"vegreferanser": [{"status": "V", "nummer": 723, "fylke": 16, "fra_meter": 17808, "til_meter": 17812, "kommune": 0, "hp": 1, "kortform": "1600 Fv723 hp1 m17808-17812", "kategori": "F"}], "vegavdelinger": [16], "kommuner": [1630], "geometri": {"srid": 32633, "wkt": "LINESTRING Z (258430.31575 7105271.95075 39.17598, 258427.60938 7105272.91992 38.97, 258426.53748 7105273.23509 38.89948)"}, "fylker": [16], "stedfestinger": [{"retning": "MED", "til_posisjon": 0.804847666365953, "veglenkeid": 72393, "kortform": "0.804435374959682-0.804847666365953@72393", "fra_posisjon": 0.804435374959682}], "regioner": [4], "strekningslengde": 4, "kontraktsomr\u00e5der": [{"navn": "1601 Fosen 2009-2014"}, {"navn": "1601 Fosen 2014-2019"}]}, "id": 272765375, "metadata": {"versjon": 1, "startdato": "1950-01-01", "type": {"id": 60, "navn": "Bru"}, "sist_modifisert": "2017-08-02 15:48:55"}}, {"egenskaper": [{"datatype": 2, "id": 1313, "datatype_tekst": "Tall", "navn": "Lengde", "enhet": {"kortnavn": "m", "id": 1, "navn": "Meter"}, "verdi": 4.8}, {"datatype": 2, "id": 1971, "datatype_tekst": "Tall", "navn": "Lengste spenn", "enhet": {"kortnavn": "m", "id": 1, "navn": "Meter"}, "verdi": 4.3}, {"datatype": 1, "datatype_tekst": "Tekst", "verdi": "Nordre Lunnfjordbrua", "id": 1080, "navn": "Navn"}, {"datatype": 30, "navn": "Vedlikeholdsansvarlig", "datatype_tekst": "FlerverdiAttributt, Tekst", "id": 8969, "enum_id": 11812, "verdi": "Vegvesenet/Fylkeskommunen"}, {"datatype": 30, "navn": "Materialtype", "datatype_tekst": "FlerverdiAttributt, Tekst", "id": 1404, "enum_id": 12325, "verdi": "Betong"}, {"datatype": 2, "datatype_tekst": "Tall", "verdi": 16, "id": 11180, "navn": "Opprinnelig F-Nr"}, {"datatype": 30, "navn": "Byggverkstype", "datatype_tekst": "FlerverdiAttributt, Tekst", "id": 9182, "enum_id": 12395, "verdi": "Platebru (211)"}, {"datatype": 2, "datatype_tekst": "Tall", "verdi": 100, "id": 2175, "navn": "Nummer"}, {"datatype": 30, "navn": "Brukategori", "datatype_tekst": "FlerverdiAttributt, Tekst", "id": 1263, "enum_id": 7304, "verdi": "Vegbru"}], "href": "https://www.utv.vegvesen.no/nvdb/api/v2/vegobjekter/60/272765392", "lokasjon": {"vegreferanser": [{"status": "V", "nummer": 723, "fylke": 16, "fra_meter": 23746, "til_meter": 23751, "kommune": 0, "hp": 1, "kortform": "1600 Fv723 hp1 m23746-23751", "kategori": "F"}], "vegavdelinger": [16], "kommuner": [1630], "geometri": {"srid": 32633, "wkt": "LINESTRING Z (259134.11833 7108921.83914 13.48557, 259137.74285 7108925.28001 13.60612)"}, "fylker": [16], "stedfestinger": [{"retning": "MED", "til_posisjon": 0.423441246680656, "veglenkeid": 72394, "kortform": "0.422917927993611-0.423441246680656@72394", "fra_posisjon": 0.422917927993611}], "regioner": [4], "strekningslengde": 5, "kontraktsomr\u00e5der": [{"navn": "1601 Fosen 2009-2014"}, {"navn": "1601 Fosen 2014-2019"}]}, "id": 272765392, "metadata": {"versjon": 1, "startdato": "1950-01-01", "type": {"id": 60, "navn": "Bru"}, "sist_modifisert": "2017-08-02 15:48:55"}}, {"egenskaper": [{"datatype": 2, "id": 1313, "datatype_tekst": "Tall", "navn": "Lengde", "enhet": {"kortnavn": "m", "id": 1, "navn": "Meter"}, "verdi": 3.5}, {"datatype": 2, "id": 1971, "datatype_tekst": "Tall", "navn": "Lengste spenn", "enhet": {"kortnavn": "m", "id": 1, "navn": "Meter"}, "verdi": 2.8}, {"datatype": 1, "datatype_tekst": "Tekst", "verdi": "S\u00f8re Lunnfjordbrua", "id": 1080, "navn": "Navn"}, {"datatype": 30, "navn": "Vedlikeholdsansvarlig", "datatype_tekst": "FlerverdiAttributt, Tekst", "id": 8969, "enum_id": 11812, "verdi": "Vegvesenet/Fylkeskommunen"}, {"datatype": 30, "navn": "Materialtype", "datatype_tekst": "FlerverdiAttributt, Tekst", "id": 1404, "enum_id": 12325, "verdi": "Betong"}, {"datatype": 2, "datatype_tekst": "Tall", "verdi": 16, "id": 11180, "navn": "Opprinnelig F-Nr"}, {"datatype": 30, "navn": "Byggverkstype", "datatype_tekst": "FlerverdiAttributt, Tekst", "id": 9182, "enum_id": 12395, "verdi": "Platebru (211)"}, {"datatype": 2, "datatype_tekst": "Tall", "verdi": 103, "id": 2175, "navn": "Nummer"}, {"datatype": 30, "navn": "Brukategori", "datatype_tekst": "FlerverdiAttributt, Tekst", "id": 1263, "enum_id": 7304, "verdi": "Vegbru"}], "href": "https://www.utv.vegvesen.no/nvdb/api/v2/vegobjekter/60/272765393", "lokasjon": {"vegreferanser": [{"status": "V", "nummer": 723, "fylke": 16, "fra_meter": 23731, "til_meter": 23735, "kommune": 0, "hp": 1, "kortform": "1600 Fv723 hp1 m23731-23735", "kategori": "F"}], "vegavdelinger": [16], "kommuner": [1630], "geometri": {"srid": 32633, "wkt": "LINESTRING Z (259123.83194 7108910.95108 12.96, 259124.66992 7108912.00977 12.96, 259126.46745 7108913.95242 13.07307)"}, "fylker": [16], "stedfestinger": [{"retning": "MED", "til_posisjon": 0.421766626882111, "veglenkeid": 72394, "kortform": "0.421347971932475-0.421766626882111@72394", "fra_posisjon": 0.421347971932475}], "regioner": [4], "strekningslengde": 4, "kontraktsomr\u00e5der": [{"navn": "1601 Fosen 2009-2014"}, {"navn": "1601 Fosen 2014-2019"}]}, "id": 272765393, "metadata": {"versjon": 1, "startdato": "1950-01-01", "type": {"id": 60, "navn": "Bru"}, "sist_modifisert": "2017-08-02 15:48:55"}}, {"egenskaper": [{"datatype": 2, "id": 1313, "datatype_tekst": "Tall", "navn": "Lengde", "enhet": {"kortnavn": "m", "id": 1, "navn": "Meter"}, "verdi": 3.95}, {"datatype": 2, "id": 1971, "datatype_tekst": "Tall", "navn": "Lengste spenn", "enhet": {"kortnavn": "m", "id": 1, "navn": "Meter"}, "verdi": 3.74}, {"datatype": 1, "datatype_tekst": "Tekst", "verdi": "L\u00f8vli", "id": 1080, "navn": "Navn"}, {"datatype": 30, "navn": "Vedlikeholdsansvarlig", "datatype_tekst": "FlerverdiAttributt, Tekst", "id": 8969, "enum_id": 11812, "verdi": "Vegvesenet/Fylkeskommunen"}, {"datatype": 30, "navn": "Materialtype", "datatype_tekst": "FlerverdiAttributt, Tekst", "id": 1404, "enum_id": 12325, "verdi": "Betong"}, {"datatype": 2, "datatype_tekst": "Tall", "verdi": 16, "id": 11180, "navn": "Opprinnelig F-Nr"}, {"datatype": 30, "navn": "Byggverkstype", "datatype_tekst": "FlerverdiAttributt, Tekst", "id": 9182, "enum_id": 12395, "verdi": "Platebru (211)"}, {"datatype": 2, "datatype_tekst": "Tall", "verdi": 112, "id": 2175, "navn": "Nummer"}, {"datatype": 30, "navn": "Brukategori", "datatype_tekst": "FlerverdiAttributt, Tekst", "id": 1263, "enum_id": 7304, "verdi": "Vegbru"}], "href": "https://www.utv.vegvesen.no/nvdb/api/v2/vegobjekter/60/272765395", "lokasjon": {"vegreferanser": [{"status": "V", "nummer": 723, "fylke": 16, "fra_meter": 22401, "til_meter": 22405, "kommune": 0, "hp": 1, "kortform": "1600 Fv723 hp1 m22401-22405", "kategori": "F"}], "vegavdelinger": [16], "kommuner": [1630], "geometri": {"srid": 32633, "wkt": "LINESTRING Z (258874.09086 7107759.61527 6.20746, 258877.60938 7107760.62891 6.09, 258877.91443 7107760.76493 6.07438)"}, "fylker": [16], "stedfestinger": [{"retning": "MED", "til_posisjon": 0.282521840204737, "veglenkeid": 72394, "kortform": "0.282103051446135-0.282521840204737@72394", "fra_posisjon": 0.282103051446135}], "regioner": [4], "strekningslengde": 4, "kontraktsomr\u00e5der": [{"navn": "1601 Fosen 2009-2014"}, {"navn": "1601 Fosen 2014-2019"}]}, "id": 272765395, "metadata": {"versjon": 1, "startdato": "1950-01-01", "type": {"id": 60, "navn": "Bru"}, "sist_modifisert": "2017-08-02 15:48:55"}}, {"egenskaper": [{"datatype": 2, "id": 1313, "datatype_tekst": "Tall", "navn": "Lengde", "enhet": {"kortnavn": "m", "id": 1, "navn": "Meter"}, "verdi": 10.4}, {"datatype": 2, "id": 1971, "datatype_tekst": "Tall", "navn": "Lengste spenn", "enhet": {"kortnavn": "m", "id": 1, "navn": "Meter"}, "verdi": 10.0}, {"datatype": 1, "datatype_tekst": "Tekst", "verdi": "P\u00f8len", "id": 1080, "navn": "Navn"}, {"datatype": 30, "navn": "Vedlikeholdsansvarlig", "datatype_tekst": "FlerverdiAttributt, Tekst", "id": 8969, "enum_id": 11812, "verdi": "Vegvesenet/Fylkeskommunen"}, {"datatype": 30, "navn": "Materialtype", "datatype_tekst": "FlerverdiAttributt, Tekst", "id": 1404, "enum_id": 12327, "verdi": "St\u00e5l"}, {"datatype": 2, "datatype_tekst": "Tall", "verdi": 16, "id": 11180, "navn": "Opprinnelig F-Nr"}, {"datatype": 30, "navn": "Byggverkstype", "datatype_tekst": "FlerverdiAttributt, Tekst", "id": 9182, "enum_id": 12477, "verdi": "St\u00e5lbjelkebru (360)"}, {"datatype": 2, "datatype_tekst": "Tall", "verdi": 379, "id": 2175, "navn": "Nummer"}, {"datatype": 30, "navn": "Brukategori", "datatype_tekst": "FlerverdiAttributt, Tekst", "id": 1263, "enum_id": 7304, "verdi": "Vegbru"}], "href": "https://www.utv.vegvesen.no/nvdb/api/v2/vegobjekter/60/272765424", "lokasjon": {"vegreferanser": [{"status": "V", "nummer": 723, "fylke": 16, "fra_meter": 18691, "til_meter": 18701, "kommune": 0, "hp": 1, "kortform": "1600 Fv723 hp1 m18691-18701", "kategori": "F"}], "vegavdelinger": [16], "kommuner": [1630], "geometri": {"srid": 32633, "wkt": "LINESTRING Z (257754.59322 7105781.47788 9.96776, 257753.99023 7105783.91016 9.98, 257752.13488 7105791.17573 9.9548)"}, "fylker": [16], "stedfestinger": [{"retning": "MED", "til_posisjon": 0.896353155586833, "veglenkeid": 72393, "kortform": "0.895323891987894-0.896353155586833@72393", "fra_posisjon": 0.895323891987894}], "regioner": [4], "strekningslengde": 10, "kontraktsomr\u00e5der": [{"navn": "1601 Fosen 2009-2014"}, {"navn": "1601 Fosen 2014-2019"}]}, "id": 272765424, "metadata": {"versjon": 1, "startdato": "1950-01-01", "type": {"id": 60, "navn": "Bru"}, "sist_modifisert": "2017-08-02 15:48:55"}}, {"egenskaper": [{"datatype": 2, "id": 1313, "datatype_tekst": "Tall", "navn": "Lengde", "enhet": {"kortnavn": "m", "id": 1, "navn": "Meter"}, "verdi": 22.0}, {"datatype": 2, "id": 1971, "datatype_tekst": "Tall", "navn": "Lengste spenn", "enhet": {"kortnavn": "m", "id": 1, "navn": "Meter"}, "verdi": 21.7}, {"datatype": 1, "datatype_tekst": "Tekst", "verdi": "\u00c5rnes komm. GSV-bru", "id": 1080, "navn": "Navn"}, {"datatype": 30, "navn": "Vedlikeholdsansvarlig", "datatype_tekst": "FlerverdiAttributt, Tekst", "id": 8969, "enum_id": 11807, "verdi": "Kommunen"}, {"datatype": 30, "navn": "Materialtype", "datatype_tekst": "FlerverdiAttributt, Tekst", "id": 1404, "enum_id": 12327, "verdi": "St\u00e5l"}, {"datatype": 2, "datatype_tekst": "Tall", "verdi": 16, "id": 11180, "navn": "Opprinnelig F-Nr"}, {"datatype": 30, "navn": "Byggverkstype", "datatype_tekst": "FlerverdiAttributt, Tekst", "id": 9182, "enum_id": 12477, "verdi": "St\u00e5lbjelkebru (360)"}, {"datatype": 2, "datatype_tekst": "Tall", "verdi": 442, "id": 2175, "navn": "Nummer"}, {"datatype": 30, "navn": "Brukategori", "datatype_tekst": "FlerverdiAttributt, Tekst", "id": 1263, "enum_id": 7306, "verdi": "G/S-bru"}], "href": "https://www.utv.vegvesen.no/nvdb/api/v2/vegobjekter/60/272765438", "lokasjon": {"vegreferanser": [{"status": "V", "nummer": 715, "fylke": 16, "fra_meter": 21090, "til_meter": 21110, "kommune": 0, "hp": 13, "kortform": "1600 Fv715 hp13 m21090-21110", "kategori": "F"}], "vegavdelinger": [16], "kommuner": [1630], "geometri": {"srid": 32633, "wkt": "LINESTRING Z (266188.89629 7101562.79125 8.76, 266188.28516 7101564.73242 8.76, 266182.62157 7101582.74463 8.76)"}, "fylker": [16], "stedfestinger": [{"sideposisjon": "L", "retning": "MED", "veglenkeid": 72859, "kortform": "0.626544558797406-0.6289700043038@72859", "til_posisjon": 0.6289700043038, "fra_posisjon": 0.626544558797406}], "regioner": [4], "strekningslengde": 20, "kontraktsomr\u00e5der": [{"navn": "1601 Fosen 2009-2014"}, {"navn": "1601 Fosen 2014-2019"}]}, "id": 272765438, "metadata": {"versjon": 1, "startdato": "1950-01-01", "type": {"id": 60, "navn": "Bru"}, "sist_modifisert": "2017-08-02 15:48:55"}}, {"egenskaper": [{"datatype": 2, "id": 1313, "datatype_tekst": "Tall", "navn": "Lengde", "enhet": {"kortnavn": "m", "id": 1, "navn": "Meter"}, "verdi": 44.44}, {"datatype": 2, "id": 1971, "datatype_tekst": "Tall", "navn": "Lengste spenn", "enhet": {"kortnavn": "m", "id": 1, "navn": "Meter"}, "verdi": 15.0}, {"datatype": 1, "datatype_tekst": "Tekst", "verdi": "Tr\u00f8mobrua", "id": 1080, "navn": "Navn"}, {"datatype": 30, "navn": "Vedlikeholdsansvarlig", "datatype_tekst": "FlerverdiAttributt, Tekst", "id": 8969, "enum_id": 11812, "verdi": "Vegvesenet/Fylkeskommunen"}, {"datatype": 30, "navn": "Materialtype", "datatype_tekst": "FlerverdiAttributt, Tekst", "id": 1404, "enum_id": 12326, "verdi": "Spennbetong"}, {"datatype": 2, "datatype_tekst": "Tall", "verdi": 16, "id": 11180, "navn": "Opprinnelig F-Nr"}, {"datatype": 30, "navn": "Byggverkstype", "datatype_tekst": "FlerverdiAttributt, Tekst", "id": 9182, "enum_id": 12452, "verdi": "Bj.bru, NOB/NOT (330)"}, {"datatype": 2, "datatype_tekst": "Tall", "verdi": 856, "id": 2175, "navn": "Nummer"}, {"datatype": 30, "navn": "Brukategori", "datatype_tekst": "FlerverdiAttributt, Tekst", "id": 1263, "enum_id": 7304, "verdi": "Vegbru"}], "href": "https://www.utv.vegvesen.no/nvdb/api/v2/vegobjekter/60/272765954", "lokasjon": {"vegreferanser": [{"status": "V", "nummer": 715, "fylke": 16, "fra_meter": 10190, "til_meter": 10235, "kommune": 0, "hp": 14, "kortform": "1600 Fv715 hp14 m10190-10235", "kategori": "F"}], "vegavdelinger": [16], "kommuner": [1630], "geometri": {"srid": 32633, "wkt": "LINESTRING Z (274200.46033 7107660.65586 73.94388, 274210.80078 7107666.29297 73.55, 274240.6451 7107680.08675 74.11097)"}, "fylker": [16], "stedfestinger": [{"retning": "MED", "til_posisjon": 0.749850310449011, "veglenkeid": 72363, "kortform": "0.745286591000425-0.749850310449011@72363", "fra_posisjon": 0.745286591000425}], "regioner": [4], "strekningslengde": 45, "kontraktsomr\u00e5der": [{"navn": "1601 Fosen 2009-2014"}, {"navn": "1601 Fosen 2014-2019"}]}, "id": 272765954, "metadata": {"versjon": 1, "startdato": "1950-01-01", "type": {"id": 60, "navn": "Bru"}, "sist_modifisert": "2017-08-02 15:48:55"}}, {"egenskaper": [{"datatype": 2, "id": 1313, "datatype_tekst": "Tall", "navn": "Lengde", "enhet": {"kortnavn": "m", "id": 1, "navn": "Meter"}, "verdi": 5.0}, {"datatype": 1, "datatype_tekst": "Tekst", "verdi": "Sagbrua", "id": 1080, "navn": "Navn"}, {"datatype": 30, "navn": "Vedlikeholdsansvarlig", "datatype_tekst": "FlerverdiAttributt, Tekst", "id": 8969, "enum_id": 11812, "verdi": "Vegvesenet/Fylkeskommunen"}, {"datatype": 30, "navn": "Materialtype", "datatype_tekst": "FlerverdiAttributt, Tekst", "id": 1404, "enum_id": 12325, "verdi": "Betong"}, {"datatype": 2, "datatype_tekst": "Tall", "verdi": 16, "id": 11180, "navn": "Opprinnelig F-Nr"}, {"datatype": 30, "navn": "Byggverkstype", "datatype_tekst": "FlerverdiAttributt, Tekst", "id": 9182, "enum_id": 12338, "verdi": "Kulvert, plassp (111)"}, {"datatype": 2, "datatype_tekst": "Tall", "verdi": 862, "id": 2175, "navn": "Nummer"}, {"datatype": 30, "navn": "Brukategori", "datatype_tekst": "FlerverdiAttributt, Tekst", "id": 1263, "enum_id": 7305, "verdi": "Bru i fylling"}], "href": "https://www.utv.vegvesen.no/nvdb/api/v2/vegobjekter/60/272765955", "lokasjon": {"vegreferanser": [{"status": "V", "nummer": 723, "fylke": 16, "fra_meter": 10263, "til_meter": 10268, "kommune": 0, "hp": 1, "kortform": "1600 Fv723 hp1 m10263-10268", "kategori": "F"}], "vegavdelinger": [16], "kommuner": [1630], "geometri": {"srid": 32633, "wkt": "LINESTRING Z (262179.16279 7104523.70025 18.45858, 262174.41491 7104522.14283 18.65437)"}, "fylker": [16], "stedfestinger": [{"retning": "MED", "til_posisjon": 0.0276508338199018, "veglenkeid": 72393, "kortform": "0.027136012464822-0.0276508338199018@72393", "fra_posisjon": 0.027136012464822}], "regioner": [4], "strekningslengde": 5, "kontraktsomr\u00e5der": [{"navn": "1601 Fosen 2009-2014"}, {"navn": "1601 Fosen 2014-2019"}]}, "id": 272765955, "metadata": {"versjon": 1, "startdato": "1950-01-01", "type": {"id": 60, "navn": "Bru"}, "sist_modifisert": "2017-08-02 15:48:55"}}, {"egenskaper": [{"datatype": 2, "id": 1313, "datatype_tekst": "Tall", "navn": "Lengde", "enhet": {"kortnavn": "m", "id": 1, "navn": "Meter"}, "verdi": 3.04}, {"datatype": 1, "datatype_tekst": "Tekst", "verdi": "Beversmark", "id": 1080, "navn": "Navn"}, {"datatype": 30, "navn": "Vedlikeholdsansvarlig", "datatype_tekst": "FlerverdiAttributt, Tekst", "id": 8969, "enum_id": 11812, "verdi": "Vegvesenet/Fylkeskommunen"}, {"datatype": 2, "datatype_tekst": "Tall", "verdi": 16, "id": 11180, "navn": "Opprinnelig F-Nr"}, {"datatype": 30, "navn": "Byggverkstype", "datatype_tekst": "FlerverdiAttributt, Tekst", "id": 9182, "enum_id": 12357, "verdi": "R\u00f8r, korrugert (14)"}, {"datatype": 2, "datatype_tekst": "Tall", "verdi": 1058, "id": 2175, "navn": "Nummer"}, {"datatype": 30, "navn": "Brukategori", "datatype_tekst": "FlerverdiAttributt, Tekst", "id": 1263, "enum_id": 7305, "verdi": "Bru i fylling"}], "href": "https://www.utv.vegvesen.no/nvdb/api/v2/vegobjekter/60/358290048", "lokasjon": {"vegreferanser": [{"status": "V", "nummer": 52, "fylke": 16, "fra_meter": 5106, "til_meter": 5109, "kommune": 0, "hp": 1, "kortform": "1600 Fv52 hp1 m5106-5109", "kategori": "F"}], "vegavdelinger": [16], "kommuner": [1630], "geometri": {"srid": 32633, "wkt": "LINESTRING Z (270730.4337 7102959.60295 28.18702, 270732.73047 7102959.17969 28.19, 270733.4033 7102959.08547 28.19979)"}, "fylker": [16], "stedfestinger": [{"retning": "MED", "til_posisjon": 0.511972620843039, "veglenkeid": 72418, "kortform": "0.511671987960602-0.511972620843039@72418", "fra_posisjon": 0.511671987960602}], "regioner": [4], "strekningslengde": 3, "kontraktsomr\u00e5der": [{"navn": "1601 Fosen 2009-2014"}, {"navn": "1601 Fosen 2014-2019"}]}, "id": 358290048, "metadata": {"versjon": 1, "startdato": "2012-09-18", "type": {"id": 60, "navn": "Bru"}, "sist_modifisert": "2017-08-02 15:48:55"}}, {"egenskaper": [{"datatype": 2, "id": 1313, "datatype_tekst": "Tall", "navn": "Lengde", "enhet": {"kortnavn": "m", "id": 1, "navn": "Meter"}, "verdi": 83.0}, {"datatype": 1, "datatype_tekst": "Tekst", "verdi": "\u00c5rnesbrua", "id": 1080, "navn": "Navn"}, {"datatype": 30, "navn": "Vedlikeholdsansvarlig", "datatype_tekst": "FlerverdiAttributt, Tekst", "id": 8969, "enum_id": 11812, "verdi": "Vegvesenet/Fylkeskommunen"}, {"datatype": 2, "datatype_tekst": "Tall", "verdi": 16, "id": 11180, "navn": "Opprinnelig F-Nr"}, {"datatype": 30, "navn": "Byggverkstype", "datatype_tekst": "FlerverdiAttributt, Tekst", "id": 9182, "enum_id": 12485, "verdi": "Plateb\u00e6rerbru (37)"}, {"datatype": 2, "datatype_tekst": "Tall", "verdi": 1200, "id": 2175, "navn": "Nummer"}, {"datatype": 30, "navn": "Brukategori", "datatype_tekst": "FlerverdiAttributt, Tekst", "id": 1263, "enum_id": 7304, "verdi": "Vegbru"}], "href": "https://www.utv.vegvesen.no/nvdb/api/v2/vegobjekter/60/360916085", "lokasjon": {"vegreferanser": [{"status": "V", "nummer": 715, "fylke": 16, "fra_meter": 21043, "til_meter": 21120, "kommune": 0, "hp": 13, "kortform": "1600 Fv715 hp13 m21043-21120", "kategori": "F"}], "vegavdelinger": [16], "kommuner": [1630], "geometri": {"srid": 32633, "wkt": "LINESTRING Z (266204.76953 7101517.00391 8.78, 266199.11719 7101531.04492 8.74, 266195.75391 7101541 8.77, 266192.31641 7101551.92773 8.76, 266188.28516 7101564.73242 8.76, 266179.76974 7101591.81446 8.76)"}, "fylker": [16], "stedfestinger": [{"retning": "MED", "til_posisjon": 0.630072479533979, "veglenkeid": 72859, "kortform": "0.620921935123494-0.630072479533979@72859", "fra_posisjon": 0.620921935123494}], "regioner": [4], "strekningslengde": 77, "kontraktsomr\u00e5der": [{"navn": "1601 Fosen 2009-2014"}, {"navn": "1601 Fosen 2014-2019"}]}, "id": 360916085, "metadata": {"versjon": 1, "startdato": "2012-10-02", "type": {"id": 60, "navn": "Bru"}, "sist_modifisert": "2017-08-02 15:48:55"}}, {"egenskaper": [{"datatype": 2, "id": 1313, "datatype_tekst": "Tall", "navn": "Lengde", "enhet": {"kortnavn": "m", "id": 1, "navn": "Meter"}, "verdi": 3.6}, {"datatype": 1, "datatype_tekst": "Tekst", "verdi": "\u00c5rnesbrua o/GSV", "id": 1080, "navn": "Navn"}, {"datatype": 30, "navn": "Vedlikeholdsansvarlig", "datatype_tekst": "FlerverdiAttributt, Tekst", "id": 8969, "enum_id": 11812, "verdi": "Vegvesenet/Fylkeskommunen"}, {"datatype": 30, "navn": "Materialtype", "datatype_tekst": "FlerverdiAttributt, Tekst", "id": 1404, "enum_id": 12325, "verdi": "Betong"}, {"datatype": 2, "datatype_tekst": "Tall", "verdi": 16, "id": 11180, "navn": "Opprinnelig F-Nr"}, {"datatype": 30, "navn": "Byggverkstype", "datatype_tekst": "FlerverdiAttributt, Tekst", "id": 9182, "enum_id": 12336, "verdi": "Kulvert, plassp (11)"}, {"datatype": 2, "datatype_tekst": "Tall", "verdi": 1201, "id": 2175, "navn": "Nummer"}, {"datatype": 30, "navn": "Brukategori", "datatype_tekst": "FlerverdiAttributt, Tekst", "id": 1263, "enum_id": 7304, "verdi": "Vegbru"}], "href": "https://www.utv.vegvesen.no/nvdb/api/v2/vegobjekter/60/360916086", "lokasjon": {"vegreferanser": [{"status": "V", "nummer": 715, "fylke": 16, "fra_meter": 21123, "til_meter": 21127, "kommune": 0, "hp": 13, "kortform": "1600 Fv715 hp13 m21123-21127", "kategori": "F"}], "vegavdelinger": [16], "kommuner": [1630], "geometri": {"srid": 32633, "wkt": "LINESTRING Z (266178.62901 7101595.44238 8.76, 266177.48828 7101599.07031 8.76)"}, "fylker": [16], "stedfestinger": [{"retning": "MED", "til_posisjon": 0.630954459718122, "veglenkeid": 72859, "kortform": "0.63051346962605-0.630954459718122@72859", "fra_posisjon": 0.63051346962605}], "regioner": [4], "strekningslengde": 4, "kontraktsomr\u00e5der": [{"navn": "1601 Fosen 2009-2014"}, {"navn": "1601 Fosen 2014-2019"}]}, "id": 360916086, "metadata": {"versjon": 1, "startdato": "2012-10-02", "type": {"id": 60, "navn": "Bru"}, "sist_modifisert": "2017-08-02 15:48:55"}}, {"egenskaper": [{"datatype": 2, "id": 1313, "datatype_tekst": "Tall", "navn": "Lengde", "enhet": {"kortnavn": "m", "id": 1, "navn": "Meter"}, "verdi": 525.0}, {"datatype": 1, "datatype_tekst": "Tekst", "verdi": "Stokk\u00f8ybrua", "id": 1080, "navn": "Navn"}, {"datatype": 30, "navn": "Vedlikeholdsansvarlig", "datatype_tekst": "FlerverdiAttributt, Tekst", "id": 8969, "enum_id": 11812, "verdi": "Vegvesenet/Fylkeskommunen"}, {"datatype": 2, "datatype_tekst": "Tall", "verdi": 16, "id": 11180, "navn": "Opprinnelig F-Nr"}, {"datatype": 30, "navn": "Byggverkstype", "datatype_tekst": "FlerverdiAttributt, Tekst", "id": 9182, "enum_id": 12547, "verdi": "Frittfremb.bru (45)"}, {"datatype": 2, "datatype_tekst": "Tall", "verdi": 1447, "id": 2175, "navn": "Nummer"}, {"datatype": 30, "navn": "Brukategori", "datatype_tekst": "FlerverdiAttributt, Tekst", "id": 1263, "enum_id": 7304, "verdi": "Vegbru"}], "href": "https://www.utv.vegvesen.no/nvdb/api/v2/vegobjekter/60/360916096", "lokasjon": {"vegreferanser": [{"status": "V", "nummer": 723, "fylke": 16, "fra_meter": 28536, "til_meter": 29061, "kommune": 0, "hp": 1, "kortform": "1600 Fv723 hp1 m28536-29061", "kategori": "F"}], "vegavdelinger": [16], "kommuner": [1630], "geometri": {"srid": 32633, "wkt": "LINESTRING Z (257966.10046 7111393.61308 15.13976, 257968.67188 7111397.07422 15.34, 257973.49609 7111404.73047 16.08, 257978.48047 7111413.13281 16.84, 257984.52734 7111424.89453 17.77, 257990.57422 7111438.67578 18.88, 257996.44531 7111453.48828 20.14, 258004.66406 7111477.48047 22.07, 258011.09375 7111495.96094 23.67, 258018.3457 7111517.27734 25.34, 258024.90039 7111536.46875 27.07, 258032.60156 7111558.62109 28.93, 258039.09375 7111577.94922 30.41, 258043.23438 7111589.96875 31.59, 258046.34766 7111598.78516 32.2, 258052.44141 7111616.57422 33.46, 258057.69336 7111631.72656 34.41, 258063.39258 7111648.76562 35.26, 258069.94531 7111667.25781 35.72, 258075.33984 7111684.25391 35.88, 258088.09766 7111720.77344 35.14, 258095.05664 7111741.22656 34.13, 258101.83008 7111760.69531 32.72, 258108.27344 7111779.62891 31.25, 258115.07617 7111799.26953 29.64, 258122.73828 7111822.19531 27.76, 258129.88867 7111842.87891 26.1, 258137.31055 7111865.04688 24.22, 258143.74414 7111883.35547 22.67, 258144.32985 7111885.29762 22.50537)"}, "fylker": [16], "stedfestinger": [{"retning": "MED", "til_posisjon": 0.979027175848239, "veglenkeid": 72394, "kortform": "0.924733066024091-0.979027175848239@72394", "fra_posisjon": 0.924733066024091}], "regioner": [4], "strekningslengde": 525, "kontraktsomr\u00e5der": [{"navn": "1601 Fosen 2009-2014"}, {"navn": "1601 Fosen 2014-2019"}]}, "id": 360916096, "metadata": {"versjon": 1, "startdato": "2012-10-02", "type": {"id": 60, "navn": "Bru"}, "sist_modifisert": "2017-08-02 15:48:55"}}, {"egenskaper": [{"datatype": 2, "id": 1313, "datatype_tekst": "Tall", "navn": "Lengde", "enhet": {"kortnavn": "m", "id": 1, "navn": "Meter"}, "verdi": 12.56}, {"datatype": 1, "datatype_tekst": "Tekst", "verdi": "Imsen", "id": 1080, "navn": "Navn"}, {"datatype": 30, "navn": "Vedlikeholdsansvarlig", "datatype_tekst": "FlerverdiAttributt, Tekst", "id": 8969, "enum_id": 11812, "verdi": "Vegvesenet/Fylkeskommunen"}, {"datatype": 2, "datatype_tekst": "Tall", "verdi": 16, "id": 11180, "navn": "Opprinnelig F-Nr"}, {"datatype": 30, "navn": "Byggverkstype", "datatype_tekst": "FlerverdiAttributt, Tekst", "id": 9182, "enum_id": 12357, "verdi": "R\u00f8r, korrugert (14)"}, {"datatype": 2, "datatype_tekst": "Tall", "verdi": 1196, "id": 2175, "navn": "Nummer"}, {"datatype": 30, "navn": "Brukategori", "datatype_tekst": "FlerverdiAttributt, Tekst", "id": 1263, "enum_id": 7305, "verdi": "Bru i fylling"}], "href": "https://www.utv.vegvesen.no/nvdb/api/v2/vegobjekter/60/360916101", "lokasjon": {"vegreferanser": [{"status": "V", "nummer": 723, "fylke": 16, "fra_meter": 5365, "til_meter": 5377, "kommune": 0, "hp": 1, "kortform": "1600 Fv723 hp1 m5365-5377", "kategori": "F"}], "vegavdelinger": [16], "kommuner": [1630], "geometri": {"srid": 32633, "wkt": "LINESTRING Z (266720.9447 7106001.49384 3.4859, 266720 7106002 3.5, 266714.2998 7106004.91016 3.5, 266710.0401 7106006.39094 3.5)"}, "fylker": [16], "stedfestinger": [{"retning": "MED", "til_posisjon": 0.537202026449358, "veglenkeid": 72392, "kortform": "0.535993303073734-0.537202026449358@72392", "fra_posisjon": 0.535993303073734}], "regioner": [4], "strekningslengde": 12, "kontraktsomr\u00e5der": [{"navn": "1601 Fosen 2009-2014"}, {"navn": "1601 Fosen 2014-2019"}]}, "id": 360916101, "metadata": {"versjon": 1, "startdato": "2012-10-02", "type": {"id": 60, "navn": "Bru"}, "sist_modifisert": "2017-08-02 15:48:55"}}, {"egenskaper": [{"datatype": 2, "id": 1313, "datatype_tekst": "Tall", "navn": "Lengde", "enhet": {"kortnavn": "m", "id": 1, "navn": "Meter"}, "verdi": 22.0}, {"datatype": 1, "datatype_tekst": "Tekst", "verdi": "Kirkholmenbrua", "id": 1080, "navn": "Navn"}, {"datatype": 30, "navn": "Vedlikeholdsansvarlig", "datatype_tekst": "FlerverdiAttributt, Tekst", "id": 8969, "enum_id": 11812, "verdi": "Vegvesenet/Fylkeskommunen"}, {"datatype": 2, "datatype_tekst": "Tall", "verdi": 16, "id": 11180, "navn": "Opprinnelig F-Nr"}, {"datatype": 30, "navn": "Byggverkstype", "datatype_tekst": "FlerverdiAttributt, Tekst", "id": 9182, "enum_id": 12476, "verdi": "St\u00e5lbjelkebru (36)"}, {"datatype": 2, "datatype_tekst": "Tall", "verdi": 1519, "id": 2175, "navn": "Nummer"}, {"datatype": 30, "navn": "Brukategori", "datatype_tekst": "FlerverdiAttributt, Tekst", "id": 1263, "enum_id": 7305, "verdi": "Bru i fylling"}], "href": "https://www.utv.vegvesen.no/nvdb/api/v2/vegobjekter/60/360916102", "lokasjon": {"vegreferanser": [{"status": "V", "nummer": 723, "fylke": 16, "fra_meter": 27642, "til_meter": 27666, "kommune": 0, "hp": 1, "kortform": "1600 Fv723 hp1 m27642-27666", "kategori": "F"}], "vegavdelinger": [16], "kommuner": [1630], "geometri": {"srid": 32633, "wkt": "LINESTRING Z (258321.871 7110883.03894 5.09698, 258321.56445 7110885.60938 5.15, 258320.11914 7110896.16797 5.26, 258317.45117 7110906.66406 5.23)"}, "fylker": [16], "stedfestinger": [{"retning": "MED", "til_posisjon": 0.833333175426351, "veglenkeid": 72394, "kortform": "0.830790426048783-0.833333175426351@72394", "fra_posisjon": 0.830790426048783}], "regioner": [4], "strekningslengde": 24, "kontraktsomr\u00e5der": [{"navn": "1601 Fosen 2009-2014"}, {"navn": "1601 Fosen 2014-2019"}]}, "id": 360916102, "metadata": {"versjon": 1, "startdato": "2012-10-02", "type": {"id": 60, "navn": "Bru"}, "sist_modifisert": "2017-08-02 15:48:55"}}, {"egenskaper": [{"datatype": 2, "id": 1313, "datatype_tekst": "Tall", "navn": "Lengde", "enhet": {"kortnavn": "m", "id": 1, "navn": "Meter"}, "verdi": 315.0}, {"datatype": 1, "datatype_tekst": "Tekst", "verdi": "Lines\u00f8ybrua", "id": 1080, "navn": "Navn"}, {"datatype": 30, "navn": "Vedlikeholdsansvarlig", "datatype_tekst": "FlerverdiAttributt, Tekst", "id": 8969, "enum_id": 11812, "verdi": "Vegvesenet/Fylkeskommunen"}, {"datatype": 2, "datatype_tekst": "Tall", "verdi": 16, "id": 11180, "navn": "Opprinnelig F-Nr"}, {"datatype": 30, "navn": "Byggverkstype", "datatype_tekst": "FlerverdiAttributt, Tekst", "id": 9182, "enum_id": 12508, "verdi": "Kassebru (4)"}, {"datatype": 2, "datatype_tekst": "Tall", "verdi": 1690, "id": 2175, "navn": "Nummer"}, {"datatype": 30, "navn": "Brukategori", "datatype_tekst": "FlerverdiAttributt, Tekst", "id": 1263, "enum_id": 7304, "verdi": "Vegbru"}], "href": "https://www.utv.vegvesen.no/nvdb/api/v2/vegobjekter/60/360916104", "lokasjon": {"vegreferanser": [{"status": "V", "nummer": 34, "fylke": 16, "fra_meter": 6745, "til_meter": 7060, "kommune": 0, "hp": 1, "kortform": "1600 Fv34 hp1 m6745-7060", "kategori": "F"}], "vegavdelinger": [16], "kommuner": [1630], "geometri": {"srid": 32633, "wkt": "LINESTRING Z (252515.5243 7112391.56703 13.11314, 252459.54004 7112377.26001 18.31, 252447.70996 7112374.23999 19.31, 252435.87988 7112371.21997 20.13, 252424.02002 7112368.17993 20.76, 252412.16992 7112365.1499 21.2, 252392.65991 7112360.15991 21.78, 252380.63989 7112357.1001 21.6, 252366.82007 7112353.57007 21.68, 252353.02002 7112350.04004 21.6, 252339.21997 7112346.5 21.36, 252325.41992 7112342.97998 20.96, 252311.62012 7112339.44995 20.4, 252297.83008 7112335.92993 19.68, 252284.05005 7112332.40991 18.81, 252270.29004 7112328.88989 17.77, 252256.53003 7112325.37012 16.57, 252212.53271 7112314.12939 12.49269, 252210.10055 7112313.50801 12.2673)"}, "fylker": [16], "stedfestinger": [{"retning": "MED", "til_posisjon": 0.912393162393162, "veglenkeid": 2042426, "kortform": "0.239316239316239-0.912393162393162@2042426", "fra_posisjon": 0.239316239316239}], "regioner": [4], "strekningslengde": 315, "kontraktsomr\u00e5der": [{"navn": "1601 Fosen 2009-2014"}, {"navn": "1601 Fosen 2014-2019"}]}, "id": 360916104, "metadata": {"versjon": 1, "startdato": "2012-10-02", "type": {"id": 60, "navn": "Bru"}, "sist_modifisert": "2017-08-02 15:48:55"}}, {"egenskaper": [{"datatype": 2, "id": 1313, "datatype_tekst": "Tall", "navn": "Lengde", "enhet": {"kortnavn": "m", "id": 1, "navn": "Meter"}, "verdi": 14.8}, {"datatype": 1, "datatype_tekst": "Tekst", "verdi": "M\u00f8lslettbrua", "id": 1080, "navn": "Navn"}, {"datatype": 30, "navn": "Vedlikeholdsansvarlig", "datatype_tekst": "FlerverdiAttributt, Tekst", "id": 8969, "enum_id": 11812, "verdi": "Vegvesenet/Fylkeskommunen"}, {"datatype": 2, "datatype_tekst": "Tall", "verdi": 16, "id": 11180, "navn": "Opprinnelig F-Nr"}, {"datatype": 30, "navn": "Byggverkstype", "datatype_tekst": "FlerverdiAttributt, Tekst", "id": 9182, "enum_id": 12453, "verdi": "Bjelkebru, NOB (331)"}, {"datatype": 2, "datatype_tekst": "Tall", "verdi": 1162, "id": 2175, "navn": "Nummer"}, {"datatype": 30, "navn": "Brukategori", "datatype_tekst": "FlerverdiAttributt, Tekst", "id": 1263, "enum_id": 7304, "verdi": "Vegbru"}], "href": "https://www.utv.vegvesen.no/nvdb/api/v2/vegobjekter/60/360916110", "lokasjon": {"vegreferanser": [{"status": "V", "nummer": 715, "fylke": 16, "fra_meter": 5653, "til_meter": 5669, "kommune": 0, "hp": 14, "kortform": "1600 Fv715 hp14 m5653-5669", "kategori": "F"}], "vegavdelinger": [16], "kommuner": [1630], "geometri": {"srid": 32633, "wkt": "LINESTRING Z (270559.82533 7105087.70128 34.47046, 270569.33594 7105091.69531 33.94, 270574.12035 7105093.65509 33.64395)"}, "fylker": [16], "stedfestinger": [{"retning": "MED", "til_posisjon": 0.281605261116384, "veglenkeid": 72363, "kortform": "0.280066518398101-0.281605261116384@72363", "fra_posisjon": 0.280066518398101}], "regioner": [4], "strekningslengde": 16, "kontraktsomr\u00e5der": [{"navn": "1601 Fosen 2009-2014"}, {"navn": "1601 Fosen 2014-2019"}]}, "id": 360916110, "metadata": {"versjon": 1, "startdato": "2012-10-02", "type": {"id": 60, "navn": "Bru"}, "sist_modifisert": "2017-08-02 15:48:55"}}, {"egenskaper": [{"datatype": 2, "id": 1313, "datatype_tekst": "Tall", "navn": "Lengde", "enhet": {"kortnavn": "m", "id": 1, "navn": "Meter"}, "verdi": 7.3}, {"datatype": 1, "datatype_tekst": "Tekst", "verdi": "Grytbrua", "id": 1080, "navn": "Navn"}, {"datatype": 30, "navn": "Vedlikeholdsansvarlig", "datatype_tekst": "FlerverdiAttributt, Tekst", "id": 8969, "enum_id": 11812, "verdi": "Vegvesenet/Fylkeskommunen"}, {"datatype": 30, "navn": "Materialtype", "datatype_tekst": "FlerverdiAttributt, Tekst", "id": 1404, "enum_id": 12325, "verdi": "Betong"}, {"datatype": 2, "datatype_tekst": "Tall", "verdi": 16, "id": 11180, "navn": "Opprinnelig F-Nr"}, {"datatype": 30, "navn": "Byggverkstype", "datatype_tekst": "FlerverdiAttributt, Tekst", "id": 9182, "enum_id": 12338, "verdi": "Kulvert, plassp (111)"}, {"datatype": 2, "datatype_tekst": "Tall", "verdi": 1036, "id": 2175, "navn": "Nummer"}, {"datatype": 30, "navn": "Brukategori", "datatype_tekst": "FlerverdiAttributt, Tekst", "id": 1263, "enum_id": 7305, "verdi": "Bru i fylling"}], "href": "https://www.utv.vegvesen.no/nvdb/api/v2/vegobjekter/60/376604393", "lokasjon": {"vegreferanser": [{"status": "V", "nummer": 723, "fylke": 16, "fra_meter": 6369, "til_meter": 6376, "kommune": 0, "hp": 1, "kortform": "1600 Fv723 hp1 m6369-6376", "kategori": "F"}], "vegavdelinger": [16], "kommuner": [1630], "geometri": {"srid": 32633, "wkt": "LINESTRING Z (265770.97928 7105751.02608 13.87632, 265764.66151 7105748.1058 13.58915)"}, "fylker": [16], "stedfestinger": [{"retning": "MED", "til_posisjon": 0.637125008123271, "veglenkeid": 72392, "kortform": "0.636428178250973-0.637125008123271@72392", "fra_posisjon": 0.636428178250973}], "regioner": [4], "strekningslengde": 7, "kontraktsomr\u00e5der": [{"navn": "1601 Fosen 2009-2014"}, {"navn": "1601 Fosen 2014-2019"}]}, "id": 376604393, "metadata": {"versjon": 1, "startdato": "1950-01-01", "type": {"id": 60, "navn": "Bru"}, "sist_modifisert": "2017-08-02 15:48:55"}}, {"egenskaper": [{"datatype": 2, "id": 1313, "datatype_tekst": "Tall", "navn": "Lengde", "enhet": {"kortnavn": "m", "id": 1, "navn": "Meter"}, "verdi": 3.0}, {"datatype": 2, "id": 1971, "datatype_tekst": "Tall", "navn": "Lengste spenn", "enhet": {"kortnavn": "m", "id": 1, "navn": "Meter"}, "verdi": 0.0}, {"datatype": 1, "datatype_tekst": "Tekst", "verdi": "Purkholmen Kulvert", "id": 1080, "navn": "Navn"}, {"datatype": 30, "navn": "Vedlikeholdsansvarlig", "datatype_tekst": "FlerverdiAttributt, Tekst", "id": 8969, "enum_id": 11812, "verdi": "Vegvesenet/Fylkeskommunen"}, {"datatype": 30, "navn": "Materialtype", "datatype_tekst": "FlerverdiAttributt, Tekst", "id": 1404, "enum_id": 12325, "verdi": "Betong"}, {"datatype": 2, "datatype_tekst": "Tall", "verdi": 16, "id": 11180, "navn": "Opprinnelig F-Nr"}, {"datatype": 30, "navn": "Byggverkstype", "datatype_tekst": "FlerverdiAttributt, Tekst", "id": 9182, "enum_id": 12346, "verdi": "Kulvert, pref. (122)"}, {"datatype": 2, "datatype_tekst": "Tall", "verdi": 1346, "id": 2175, "navn": "Nummer"}, {"datatype": 30, "navn": "Brukategori", "datatype_tekst": "FlerverdiAttributt, Tekst", "id": 1263, "enum_id": 7305, "verdi": "Bru i fylling"}], "href": "https://www.utv.vegvesen.no/nvdb/api/v2/vegobjekter/60/495996675", "lokasjon": {"vegreferanser": [{"status": "V", "nummer": 723, "fylke": 16, "fra_meter": 27435, "til_meter": 27439, "kommune": 0, "hp": 1, "kortform": "1600 Fv723 hp1 m27435-27439", "kategori": "F"}], "vegavdelinger": [16], "kommuner": [1630], "geometri": {"srid": 32633, "wkt": "LINESTRING Z (258281.16229 7110685.03134 2.77, 258280.39258 7110686.62891 2.77, 258279.78736 7110688.76058 2.77)"}, "fylker": [16], "stedfestinger": [{"retning": "MED", "til_posisjon": 0.809538257428396, "veglenkeid": 72394, "kortform": "0.809124384306253-0.809538257428396@72394", "fra_posisjon": 0.809124384306253}], "regioner": [4], "strekningslengde": 4, "kontraktsomr\u00e5der": [{"navn": "1601 Fosen 2009-2014"}, {"navn": "1601 Fosen 2014-2019"}]}, "id": 495996675, "metadata": {"versjon": 1, "startdato": "1950-01-01", "type": {"id": 60, "navn": "Bru"}, "sist_modifisert": "2017-08-02 15:48:55"}}, {"egenskaper": [{"datatype": 2, "id": 1313, "datatype_tekst": "Tall", "navn": "Lengde", "enhet": {"kortnavn": "m", "id": 1, "navn": "Meter"}, "verdi": 54.0}, {"datatype": 2, "id": 1971, "datatype_tekst": "Tall", "navn": "Lengste spenn", "enhet": {"kortnavn": "m", "id": 1, "navn": "Meter"}, "verdi": 19.0}, {"datatype": 1, "datatype_tekst": "Tekst", "verdi": "Melabrua", "id": 1080, "navn": "Navn"}, {"datatype": 30, "navn": "Vedlikeholdsansvarlig", "datatype_tekst": "FlerverdiAttributt, Tekst", "id": 8969, "enum_id": 11812, "verdi": "Vegvesenet/Fylkeskommunen"}, {"datatype": 30, "navn": "Materialtype", "datatype_tekst": "FlerverdiAttributt, Tekst", "id": 1404, "enum_id": 12325, "verdi": "Betong"}, {"datatype": 2, "datatype_tekst": "Tall", "verdi": 16, "id": 11180, "navn": "Opprinnelig F-Nr"}, {"datatype": 30, "navn": "Byggverkstype", "datatype_tekst": "FlerverdiAttributt, Tekst", "id": 9182, "enum_id": 12397, "verdi": "Platebru (213)"}, {"datatype": 2, "datatype_tekst": "Tall", "verdi": 1843, "id": 2175, "navn": "Nummer"}, {"datatype": 30, "navn": "Brukategori", "datatype_tekst": "FlerverdiAttributt, Tekst", "id": 1263, "enum_id": 7304, "verdi": "Vegbru"}], "href": "https://www.utv.vegvesen.no/nvdb/api/v2/vegobjekter/60/569529829", "lokasjon": {"vegreferanser": [{"status": "V", "nummer": 715, "fylke": 16, "fra_meter": 20731, "til_meter": 20746, "kommune": 0, "hp": 13, "kortform": "1600 Fv715 hp13 m20731-20746", "kategori": "F"}], "vegavdelinger": [16], "kommuner": [1630], "geometri": {"srid": 32633, "wkt": "LINESTRING Z (266353.31067 7101244.75207 5.99503, 266345.72211 7101257.6718 5.927)"}, "fylker": [16], "stedfestinger": [{"retning": "MED", "til_posisjon": 0.788990825688073, "veglenkeid": 2661372, "kortform": "0.720183486238532-0.788990825688073@2661372", "fra_posisjon": 0.720183486238532}], "regioner": [4], "strekningslengde": 15, "kontraktsomr\u00e5der": [{"navn": "1601 Fosen 2014-2019"}]}, "id": 569529829, "metadata": {"versjon": 0, "startdato": "1950-01-01", "type": {"id": 60, "navn": "Bru"}, "sist_modifisert": "2017-08-02 15:48:55"}}], "metadata": {"neste": {"start": "gHVddU1ZYz88", "href": "https://www.utv.vegvesen.no/nvdb/api/v2/vegobjekter/60?segmentering=true&kartutsnitt=242013%2C7101048%2C273171%2C7117325&start=gHVddU1ZYz88&inkluder=lokasjon%2Cegenskaper%2Cmetadata"}, "returnert": 23}}